llm_coder/__init__.py
llm_coder/agent.py
llm_coder/cli.py
llm_coder/filesystem.py
llm_coder/litellm_cli.py
llm_coder/shell_command.py
llm_coder-0.0.4.dist-info/licenses/LICENSE
llm_coder-0.0.4.dist-info/METADATA
llm_coder-0.0.4.dist-info/WHEEL
llm_coder-0.0.4.dist-info/entry_points.txt
llm_coder-0.0.4.dist-info/top_level.txt
llm_coder-0.0.4.dist-info/RECORD
