Metadata-Version: 2.4
Name: llm-coder
Version: 0.0.4
Summary: llm による自立型 Cli コーディングエージェントライブラリ
Author-email: igtm <llm-coder@igtm.link>
License: MIT
Project-URL: Homepage, https://github.com/igtm/llm-coder
Project-URL: Bug Tracker, https://github.com/igtm/llm-coder/issues
Classifier: Programming Language :: Python :: 3
Classifier: Programming Language :: Python :: 3.11
Classifier: License :: OSI Approved :: MIT License
Classifier: Operating System :: OS Independent
Classifier: Intended Audience :: Developers
Classifier: Environment :: Console
Classifier: Topic :: Software Development :: Libraries :: Application Frameworks
Requires-Python: >=3.11
License-File: LICENSE
Requires-Dist: litellm
Requires-Dist: toml
Requires-Dist: structlog
Dynamic: license-file
